CHANGES.rst
CONTRIBUTORS.rst
MANIFEST.in
README.rst
setup.cfg
setup.py
docs/LICENSE.GPL
docs/LICENSE.rst
docs/index.rst
src/redturtle/__init__.py
src/redturtle.patterns.slider.egg-info/PKG-INFO
src/redturtle.patterns.slider.egg-info/SOURCES.txt
src/redturtle.patterns.slider.egg-info/dependency_links.txt
src/redturtle.patterns.slider.egg-info/entry_points.txt
src/redturtle.patterns.slider.egg-info/namespace_packages.txt
src/redturtle.patterns.slider.egg-info/not-zip-safe
src/redturtle.patterns.slider.egg-info/requires.txt
src/redturtle.patterns.slider.egg-info/top_level.txt
src/redturtle/patterns/__init__.py
src/redturtle/patterns/slider/__init__.py
src/redturtle/patterns/slider/configure.zcml
src/redturtle/patterns/slider/interfaces.py
src/redturtle/patterns/slider/setuphandlers.py
src/redturtle/patterns/slider/libraries/slick/slick.css
src/redturtle/patterns/slider/libraries/slick/slick.min.js
src/redturtle/patterns/slider/profiles/default/browserlayer.xml
src/redturtle/patterns/slider/profiles/default/metadata.xml
src/redturtle/patterns/slider/profiles/default/registry.xml
src/redturtle/patterns/slider/profiles/uninstall/browserlayer.xml
src/redturtle/patterns/slider/static/bundle.js
src/redturtle/patterns/slider/static/pattern.compiled.css
src/redturtle/patterns/slider/static/pattern.css
src/redturtle/patterns/slider/static/pattern.css.map
src/redturtle/patterns/slider/static/pattern.js
src/redturtle/patterns/slider/static/pattern.scss
src/redturtle/patterns/slider/static/build/redturtle-patterns-slider-bundle-compiled.js
src/redturtle/patterns/slider/static/build/redturtle-patterns-slider-bundle-compiled.js.map
src/redturtle/patterns/slider/static/build/redturtle-patterns-slider-bundle-compiled.min.css
src/redturtle/patterns/slider/static/build/redturtle-patterns-slider-bundle-compiled.min.css.map