Metadata-Version: 2.1
Name: redturtle.patterns.slider
Version: 0.1.2
Summary: An additional pattern for Mockup that provides a slider.
Home-page: https://github.com/RedTurtle/redturtle.patterns.slider
Author: Redturtle Dev Team
Author-email: sviluppoplone@redturtle.it
License: GPL version 2
Keywords: Python Plone
Platform: UNKNOWN
Classifier: Environment :: Web Environment
Classifier: Framework :: Plone
Classifier: Framework :: Plone :: 5.0
Classifier: Programming Language :: Python
Classifier: Programming Language :: Python :: 2.7
Classifier: Operating System :: OS Independent
Classifier: License :: OSI Approved :: GNU General Public License v2 (GPLv2)
Provides-Extra: test
